{
  "projectId": 1713,
  "stationId": 5578,
  "problemBankId": 921,
  "problemBankCreatedBy": "planning@bits.com",
  "stationCreatedBy": "planning@bits.com",
  "stationCreatedStudentName": null,
  "isStationCreatedByStudent": false,
  "title": "Details Awaited",
  "description": "<p>-</p>",
  "pstypeId": 2,
  "batchId": 16,
  "semesterId": 1,
  "salutation": "Mr.",
  "mentorName": "",
  "mentorEmailId": "",
  "mentorContactNumber": "",
  "discViewModels": [
    {
      "projectId": 1713,
      "projectDisciplineId": 5056,
      "projectDisciplineCodes": "AnyA3,AnyA7,AnyAA,AnyA8,A3,A7,A8,AA",
      "discCodesPerProject": "AnyA3,AnyA7,AnyAA,AnyA8,A3,A7,A8,AA",
      "graduationTypeIds": [
        1
      ],
      "anySingle": false,
      "anyDual": false,
      "anyEither": false,
      "anyHigher": false,
      "anyDegree": false
    }
  ],
  "projectDiscipline": [
    {
      "projectDisciplineId": 5056,
      "projectId": 1713,
      "degreeTypeId": 3,
      "firstDegree": 1,
      "higherDegree": 0,
      "cgpamin": 8,
      "cgpamax": 10,
      "freshRequirement": 6,
      "totalRequirement": 6,
      "maleRequirement": 0,
      "femaleRequirement": 0,
      "continuingStudent": 0,
      "disciplineCodes": "AnyA3,AnyA7,AnyAA,AnyA8,A3,A7,A8,AA",
      "graduationTypeIds": [
        0,
        1
      ],
      "degree": "Both",
      "continuingStudentCount": 0,
      "continuingStudentIds": null,
      "conditionalOffer": 0,
      "conditionalOfferCount": 0,
      "otherConstraint": 0,
      "otherConstraintCount": 0,
      "otherSuggestedStation": 0,
      "anyDualDegree": 0,
      "disciplineDetails": [
        {
          "projectDisciplineDetailId": 13906,
          "projectDisciplineId": 5056,
          "graduationTypeId": 0,
          "disciplineId": null,
          "discipline2Id": 3
        },
        {
          "projectDisciplineDetailId": 13907,
          "projectDisciplineId": 5056,
          "graduationTypeId": 0,
          "disciplineId": null,
          "discipline2Id": 12
        },
        {
          "projectDisciplineDetailId": 13908,
          "projectDisciplineId": 5056,
          "graduationTypeId": 0,
          "disciplineId": null,
          "discipline2Id": 14
        },
        {
          "projectDisciplineDetailId": 13909,
          "projectDisciplineId": 5056,
          "graduationTypeId": 0,
          "disciplineId": null,
          "discipline2Id": 13
        },
        {
          "projectDisciplineDetailId": 13910,
          "projectDisciplineId": 5056,
          "graduationTypeId": 1,
          "disciplineId": 3,
          "discipline2Id": null
        },
        {
          "projectDisciplineDetailId": 13911,
          "projectDisciplineId": 5056,
          "graduationTypeId": 1,
          "disciplineId": 12,
          "discipline2Id": null
        },
        {
          "projectDisciplineDetailId": 13912,
          "projectDisciplineId": 5056,
          "graduationTypeId": 1,
          "disciplineId": 13,
          "discipline2Id": null
        },
        {
          "projectDisciplineDetailId": 13913,
          "projectDisciplineId": 5056,
          "graduationTypeId": 1,
          "disciplineId": 14,
          "discipline2Id": null
        }
      ],
      "selectedContinuingStudentList": null,
      "conditionalOfferStudents": null
    }
  ],
  "projectElective": [],
  "projectFacility": [
    {
      "projectFacilityId": 1633,
      "projectId": 1713,
      "officeStartTime": "09:00:00",
      "officeEndTime": "18:00:00",
      "weekHolidays": "Saturday,Sunday",
      "ugstipend": 40000,
      "pgstipend": 0,
      "scholarship": null,
      "currency": "INR",
      "subsidizedLunch": 2,
      "boysAccommodation": 0,
      "girlsAccommodation": 0,
      "accomodationAddress": "",
      "ta": 2,
      "da": 2,
      "conveyance": 2,
      "medical": 2,
      "travels": 2,
      "others": "",
      "boysAccomodationAddress1": "",
      "boysAccomodationAddress2": "",
      "boysAccomodationCity": null,
      "boysAccomodationState": null,
      "boysAccomodationCountry": null,
      "boysAccomodationPincode": "",
      "girlsAccomodationAddress1": "",
      "girlsAccomodationAddress2": "",
      "girlsAccomodationCity": null,
      "girlsAccomodationState": null,
      "girlsAccomodationCountry": null,
      "girlsAccomodationPincode": "",
      "createdBy": "planning@bits.com",
      "createdDate": "2024-05-18T07:32:41",
      "modifiedBy": null,
      "modifiedDate": null,
      "girlsAccomodationOtherCityName": null,
      "boysAccomodationOtherCityName": null,
      "girlsAccomodationCityName": null,
      "boysAccomodationCityName": null
    }
  ],
  "projectSkill": [
    {
      "projectSkillId": 37122,
      "projectId": 1713,
      "skillId": 132
    },
    {
      "projectSkillId": 37123,
      "projectId": 1713,
      "skillId": 141
    }
  ],
  "projectAcademicDomain": [
    {
      "projectId": 1713,
      "projectDomainId": 2437,
      "academicDomainId": 28
    }
  ],
  "projectSubjectAreaSpecifics": [],
  "projectAcademicSubDomain": [
    {
      "projectSubDomainId": 2241,
      "projectId": 1713,
      "academicSubDomainId": 133
    }
  ],
  "projectSubjectArea": [],
  "continuingStudents": null
}