{
  "problemBankGridLines": null,
  "projectGridLines": [
    {
      "stationId": 4719,
      "stationName": "Immensitas Pvt. Ltd. (Lemnisk)",
      "stationCity": null,
      "businessDomain": "CSIS/IT",
      "problemBankId": 841,
      "projectId": 1557,
      "semesterId": 1,
      "pstypeId": 2,
      "psType": "PS II",
      "batchId": 16,
      "batch": "2024-25",
      "title": "Events Backend",
      "description": "<p>Feature developments with respect to millions of events being received in real time and processing and modification and storing of those in real time.</p><p>Language: Java. DB: NoSQL, MySQL</p><p>Expected Learning : </p><ul><li>Production scale Software development</li><li>Personal development in terms of how to scale things</li><li>with millions of events in production</li></ul>",
      "projectDomain": "",
      "projectSubDomain": null,
      "ugStipend": 35000,
      "pgStipend": 0,
      "totalMaleRequirement": 0,
      "totalFemalRequirement": 0,
      "totalRequirment": 0,
      "discipline": "",
      "sumOfStipend": 35000,
      "createdBy": "planning@bits.com",
      "assignedFacultyEmailId": "raja.vadhana@pilani.bits-pilani.ac.in",
      "studentProjectDetails": null
    }
  ]
}