{
  "problemBankGridLines": [
    {
      "stationId": 6359,
      "stationName": "Champion InfoMetrics Pvt Ltd",
      "parentStationName": "Champion InfoMetrics Pvt Ltd",
      "stationCity": "Bengaluru",
      "problemBankId": 2220,
      "businessDomain": "Finance and Mgmt",
      "totalFemalRequirement": 0,
      "totalMaleRequirement": 0,
      "totalRequirement": 0,
      "noOfProject": 1,
      "batchId": 16,
      "psTypeId": 2,
      "psTypeName": "PS II",
      "semesterId": 2,
      "status": null,
      "createdBy": "planning@bits.com"
    },
    {
      "stationId": 6359,
      "stationName": "Champion InfoMetrics Pvt Ltd",
      "parentStationName": "Champion InfoMetrics Pvt Ltd",
      "stationCity": "Bengaluru",
      "problemBankId": 2221,
      "businessDomain": "Finance and Mgmt",
      "totalFemalRequirement": 0,
      "totalMaleRequirement": 0,
      "totalRequirement": 0,
      "noOfProject": 1,
      "batchId": 16,
      "psTypeId": 2,
      "psTypeName": "PS II",
      "semesterId": 2,
      "status": null,
      "createdBy": "planning@bits.com"
    },
    {
      "stationId": 6359,
      "stationName": "Champion InfoMetrics Pvt Ltd",
      "parentStationName": "Champion InfoMetrics Pvt Ltd",
      "stationCity": "Bengaluru",
      "problemBankId": 2222,
      "businessDomain": "Finance and Mgmt",
      "totalFemalRequirement": 0,
      "totalMaleRequirement": 0,
      "totalRequirement": 0,
      "noOfProject": 1,
      "batchId": 16,
      "psTypeId": 2,
      "psTypeName": "PS II",
      "semesterId": 2,
      "status": null,
      "createdBy": "planning@bits.com"
    },
    {
      "stationId": 6359,
      "stationName": "Champion InfoMetrics Pvt Ltd",
      "parentStationName": "Champion InfoMetrics Pvt Ltd",
      "stationCity": "Bengaluru",
      "problemBankId": 2223,
      "businessDomain": "Finance and Mgmt",
      "totalFemalRequirement": 0,
      "totalMaleRequirement": 0,
      "totalRequirement": 0,
      "noOfProject": 1,
      "batchId": 16,
      "psTypeId": 2,
      "psTypeName": "PS II",
      "semesterId": 2,
      "status": null,
      "createdBy": "planning@bits.com"
    },
    {
      "stationId": 6359,
      "stationName": "Champion InfoMetrics Pvt Ltd",
      "parentStationName": "Champion InfoMetrics Pvt Ltd",
      "stationCity": "Bengaluru",
      "problemBankId": 2224,
      "businessDomain": "Finance and Mgmt",
      "totalFemalRequirement": 0,
      "totalMaleRequirement": 0,
      "totalRequirement": 0,
      "noOfProject": 1,
      "batchId": 16,
      "psTypeId": 2,
      "psTypeName": "PS II",
      "semesterId": 2,
      "status": null,
      "createdBy": "planning@bits.com"
    }
  ],
  "projectGridLines": null
}