{
  "problemBankGridLines": null,
  "projectGridLines": [
    {
      "stationId": 5528,
      "stationName": "TERAWATT TESTING AND RESEARCH INSTITUTE PRIVATE LIMITED",
      "stationCity": null,
      "businessDomain": "Others",
      "problemBankId": 862,
      "projectId": 1603,
      "semesterId": 1,
      "pstypeId": 2,
      "psType": "PS II",
      "batchId": 16,
      "batch": "2024-25",
      "title": "Implementation of ISO/IEC17025: 2017",
      "description": "<p>Description: ISO/IEC17025: 2017 defines the general requirements for the competence of testing and</p><p>calibration laboratories</p><p>Skill sets: MS Office Suite,</p><p>Traits expectation:</p><p>Expected learning:</p><p>? Implementation of Quality aspects as per ISO/IEC 17025:2017 in a testing/calibration</p><p>laboratory.</p><p>? Learning about lab accreditation</p><p>? Database management</p><p>? Personnel management</p><p>? Preparing test reports</p><p>Specific courses required for project execution: Should go through ISO 17025:2017, ISO 9001:2015</p><p>standard, Guide to the expression of uncertainty in measurement, Basic knowledge of Solar PV</p><p>panels and pumps</p>",
      "projectDomain": "",
      "projectSubDomain": null,
      "ugStipend": 20000,
      "pgStipend": 0,
      "totalMaleRequirement": 0,
      "totalFemalRequirement": 0,
      "totalRequirment": 0,
      "discipline": "",
      "sumOfStipend": 20000,
      "createdBy": "planning@bits.com",
      "assignedFacultyEmailId": "bhamidipati.vaishali@pilani.bits-pilani.ac.in",
      "studentProjectDetails": null
    },
    {
      "stationId": 5528,
      "stationName": "TERAWATT TESTING AND RESEARCH INSTITUTE PRIVATE LIMITED",
      "stationCity": null,
      "businessDomain": "Others",
      "problemBankId": 862,
      "projectId": 1606,
      "semesterId": 1,
      "pstypeId": 2,
      "psType": "PS II",
      "batchId": 16,
      "batch": "2024-25",
      "title": "Implementation of testing setup as per BIS Standards for Water Pumping Systems and Solar PV  Modules",
      "description": "<p>Description:</p><p>Skill sets: Electrical connections and working with DC and AC Energy.</p><p>Traits expectation: Knowledge of Motor designs</p><p>Expected learning:</p><p>? Testing of Water Pumping Systems for Hydraulic as well as electrical testing using Solar Array</p><p>Simulators.</p><p>? Testing of Solar PV Modules</p><p>? Calibration of measuring equipment</p><p>? Preparing test reports</p><p>? Calculation of Measurement uncertainty</p><p>? Maintenance of equipment</p><p>Specific courses required for project execution: Should go through ISO 17025:2017, ISO 9001:2015</p><p>standard, Guide to the expression of uncertainty in measurement, Basic knowledge of Solar PV</p><p>panels and pumps, IEC 61215/IS14286, IEC60904, IS 12762, IS 8034, IS 9283, IS 11346, IEC 62253.</p>",
      "projectDomain": "",
      "projectSubDomain": null,
      "ugStipend": 20000,
      "pgStipend": 0,
      "totalMaleRequirement": 0,
      "totalFemalRequirement": 0,
      "totalRequirment": 0,
      "discipline": "",
      "sumOfStipend": 20000,
      "createdBy": "planning@bits.com",
      "assignedFacultyEmailId": "bhamidipati.vaishali@pilani.bits-pilani.ac.in",
      "studentProjectDetails": null
    }
  ]
}