{
  "problemBankGridLines": null,
  "projectGridLines": [
    {
      "stationId": 5594,
      "stationName": "Goodera - GTM",
      "stationCity": null,
      "businessDomain": "CSIS/IT",
      "problemBankId": 947,
      "projectId": 1748,
      "semesterId": 1,
      "pstypeId": 2,
      "psType": "PS II",
      "batchId": 16,
      "batch": "2024-25",
      "title": "Project - marketing/process improvement",
      "description": "<p>Project - marketing/process improvement</p>",
      "projectDomain": "",
      "projectSubDomain": null,
      "ugStipend": 35000,
      "pgStipend": 0,
      "totalMaleRequirement": 0,
      "totalFemalRequirement": 0,
      "totalRequirment": 0,
      "discipline": "",
      "sumOfStipend": 35000,
      "createdBy": "planning@bits.com",
      "assignedFacultyEmailId": "sandeep.kayastha@pilani.bits-pilani.ac.in",
      "studentProjectDetails": null
    }
  ]
}