{
  "projectId": 2160,
  "stationId": 5754,
  "problemBankId": 1209,
  "problemBankCreatedBy": "planning@bits.com",
  "stationCreatedBy": "planning@bits.com",
  "stationCreatedStudentName": null,
  "isStationCreatedByStudent": false,
  "title": "Analytics - Sentimental Analysis of Product Reviews",
  "description": "<p class=\"ql-align-justify\"><br></p><p class=\"ql-align-justify\"><strong style=\"background-color: transparent; color: rgb(0, 0, 0);\">Description: </strong><span style=\"background-color: transparent; color: rgb(0, 0, 0);\">Develop model to evaluating words in different product reviews in order &nbsp;to define sentiments and opinions which may be favorable or unfavorable in polarity. This is a classification in which the classifications are either binary (optimistic or pessimistic) or multiple (happy, angry, sad, disgusted, etc.).</span><strong style=\"background-color: transparent; color: rgb(0, 0, 0);\">&nbsp;</strong></p><p class=\"ql-align-justify\"><strong style=\"background-color: transparent; color: rgb(0, 0, 0);\">Skill sets: </strong><span style=\"background-color: transparent; color: rgb(0, 0, 0);\">Excel , Python (Preferred)</span></p><p><strong style=\"background-color: transparent; color: rgb(0, 0, 0);\">Expected learning: </strong><span style=\"background-color: transparent; color: rgb(0, 0, 0);\">Understanding of supervised learning and basic NLP</span></p>",
  "pstypeId": 2,
  "batchId": 16,
  "semesterId": 1,
  "salutation": "Mr.",
  "mentorName": "",
  "mentorEmailId": "",
  "mentorContactNumber": "",
  "discViewModels": [
    {
      "projectId": 2160,
      "projectDisciplineId": 5019,
      "projectDisciplineCodes": "A7,AnyA7",
      "discCodesPerProject": "A7,AnyA7",
      "graduationTypeIds": [
        1
      ],
      "anySingle": false,
      "anyDual": false,
      "anyEither": false,
      "anyHigher": false,
      "anyDegree": false
    }
  ],
  "projectDiscipline": [
    {
      "projectDisciplineId": 5019,
      "projectId": 2160,
      "degreeTypeId": 3,
      "firstDegree": 1,
      "higherDegree": 0,
      "cgpamin": 0,
      "cgpamax": 10,
      "freshRequirement": 1,
      "totalRequirement": 1,
      "maleRequirement": 0,
      "femaleRequirement": 0,
      "continuingStudent": 0,
      "disciplineCodes": "A7,AnyA7",
      "graduationTypeIds": [
        1,
        0
      ],
      "degree": "Both",
      "continuingStudentCount": 0,
      "continuingStudentIds": null,
      "conditionalOffer": 0,
      "conditionalOfferCount": 0,
      "otherConstraint": 0,
      "otherConstraintCount": 0,
      "otherSuggestedStation": 0,
      "anyDualDegree": 0,
      "disciplineDetails": [
        {
          "projectDisciplineDetailId": 13713,
          "projectDisciplineId": 5019,
          "graduationTypeId": 1,
          "disciplineId": 12,
          "discipline2Id": null
        },
        {
          "projectDisciplineDetailId": 13714,
          "projectDisciplineId": 5019,
          "graduationTypeId": 0,
          "disciplineId": null,
          "discipline2Id": 12
        }
      ],
      "selectedContinuingStudentList": null,
      "conditionalOfferStudents": null
    }
  ],
  "projectElective": [],
  "projectFacility": [
    {
      "projectFacilityId": 2075,
      "projectId": 2160,
      "officeStartTime": "08:00:00",
      "officeEndTime": "17:30:00",
      "weekHolidays": "Saturday,Sunday",
      "ugstipend": 40000,
      "pgstipend": 0,
      "scholarship": null,
      "currency": "INR",
      "subsidizedLunch": 2,
      "boysAccommodation": 0,
      "girlsAccommodation": 0,
      "accomodationAddress": "",
      "ta": 2,
      "da": 2,
      "conveyance": 2,
      "medical": 2,
      "travels": 2,
      "others": "",
      "boysAccomodationAddress1": "",
      "boysAccomodationAddress2": "",
      "boysAccomodationCity": null,
      "boysAccomodationState": null,
      "boysAccomodationCountry": null,
      "boysAccomodationPincode": "",
      "girlsAccomodationAddress1": "",
      "girlsAccomodationAddress2": "",
      "girlsAccomodationCity": null,
      "girlsAccomodationState": null,
      "girlsAccomodationCountry": null,
      "girlsAccomodationPincode": "",
      "createdBy": "planning@bits.com",
      "createdDate": "2024-05-30T07:23:45",
      "modifiedBy": "planning@bits.com",
      "modifiedDate": "2024-06-13T04:57:28",
      "girlsAccomodationOtherCityName": null,
      "boysAccomodationOtherCityName": null,
      "girlsAccomodationCityName": null,
      "boysAccomodationCityName": null
    }
  ],
  "projectSkill": [
    {
      "projectSkillId": 50610,
      "projectId": 2160,
      "skillId": 431
    },
    {
      "projectSkillId": 50611,
      "projectId": 2160,
      "skillId": 141
    }
  ],
  "projectAcademicDomain": [
    {
      "projectId": 2160,
      "projectDomainId": 3059,
      "academicDomainId": 4
    }
  ],
  "projectSubjectAreaSpecifics": [],
  "projectAcademicSubDomain": [
    {
      "projectSubDomainId": 2801,
      "projectId": 2160,
      "academicSubDomainId": 13
    }
  ],
  "projectSubjectArea": [],
  "continuingStudents": null
}