{
  "problemBankGridLines": [
    {
      "stationId": 6366,
      "stationName": "Astera Labs",
      "parentStationName": "Astera Labs",
      "stationCity": "Bangalore",
      "problemBankId": 2237,
      "businessDomain": "Electronics",
      "totalFemalRequirement": 0,
      "totalMaleRequirement": 0,
      "totalRequirement": 0,
      "noOfProject": 1,
      "batchId": 16,
      "psTypeId": 2,
      "psTypeName": "PS II",
      "semesterId": 2,
      "status": null,
      "createdBy": "planning@bits.com"
    }
  ],
  "projectGridLines": null
}